aliyunsdkvod/__init__.py
aliyunsdkvod/endpoint.py
aliyunsdkvod/request/__init__.py
aliyunsdkvod/request/v20170321/AddAITemplateRequest.py
aliyunsdkvod/request/v20170321/AddCategoryRequest.py
aliyunsdkvod/request/v20170321/AddEditingProjectMaterialsRequest.py
aliyunsdkvod/request/v20170321/AddEditingProjectRequest.py
aliyunsdkvod/request/v20170321/AddTranscodeTemplateGroupRequest.py
aliyunsdkvod/request/v20170321/AddVodDomainRequest.py
aliyunsdkvod/request/v20170321/AddVodStorageForAppRequest.py
aliyunsdkvod/request/v20170321/AddVodTemplateRequest.py
aliyunsdkvod/request/v20170321/AddWatermarkRequest.py
aliyunsdkvod/request/v20170321/AttachAppPolicyToIdentityRequest.py
aliyunsdkvod/request/v20170321/BatchGetMediaInfosRequest.py
aliyunsdkvod/request/v20170321/BatchSetVodDomainConfigsRequest.py
aliyunsdkvod/request/v20170321/BatchStartVodDomainRequest.py
aliyunsdkvod/request/v20170321/BatchStopVodDomainRequest.py
aliyunsdkvod/request/v20170321/CancelUrlUploadJobsRequest.py
aliyunsdkvod/request/v20170321/ChangeResourceGroupRequest.py
aliyunsdkvod/request/v20170321/CreateAppInfoRequest.py
aliyunsdkvod/request/v20170321/CreateAuditRequest.py
aliyunsdkvod/request/v20170321/CreateUploadAttachedMediaRequest.py
aliyunsdkvod/request/v20170321/CreateUploadImageRequest.py
aliyunsdkvod/request/v20170321/CreateUploadVideoRequest.py
aliyunsdkvod/request/v20170321/DecryptKMSDataKeyRequest.py
aliyunsdkvod/request/v20170321/DeleteAIImageInfosRequest.py
aliyunsdkvod/request/v20170321/DeleteAITemplateRequest.py
aliyunsdkvod/request/v20170321/DeleteAppInfoRequest.py
aliyunsdkvod/request/v20170321/DeleteAttachedMediaRequest.py
aliyunsdkvod/request/v20170321/DeleteCategoryRequest.py
aliyunsdkvod/request/v20170321/DeleteDynamicImageRequest.py
aliyunsdkvod/request/v20170321/DeleteEditingProjectMaterialsRequest.py
aliyunsdkvod/request/v20170321/DeleteEditingProjectRequest.py
aliyunsdkvod/request/v20170321/DeleteImageRequest.py
aliyunsdkvod/request/v20170321/DeleteMessageCallbackRequest.py
aliyun_python_sdk_vod-2.16.32.dist-info/LICENSE
aliyun_python_sdk_vod-2.16.32.dist-info/METADATA
aliyun_python_sdk_vod-2.16.32.dist-info/WHEEL
aliyun_python_sdk_vod-2.16.32.dist-info/top_level.txt
aliyun_python_sdk_vod-2.16.32.dist-info/RECORD
